Metadata-Version: 1.1
Name: posixfs
Version: 1.0.1
Summary: provides atomic and durable writes on a posix file system.
Home-page: https://github.com/Parquery/posixfs
Author: Marko Ristin
Author-email: marko@parquery.com
License: UNKNOWN
Keywords: posix file system atomic durable write
Platform: UNKNOWN
Classifier: Development Status :: 5 - Production/Stable
Classifier: Intended Audience :: Developers
Classifier: License :: OSI Approved :: MIT License
Classifier: Programming Language :: Python :: 3.5
